benchmarktool/__init__.py
benchmarktool/entry_points.py
benchmarktool/tools.py
benchmarktool/init/programs/gcat.sh
benchmarktool/init/runscripts/runscript-all.xml
benchmarktool/init/runscripts/runscript-dist.xml
benchmarktool/init/runscripts/runscript-example.xml
benchmarktool/init/runscripts/runscript-seq.xml
benchmarktool/init/templates/seq-generic.sh
benchmarktool/init/templates/single.dist
benchmarktool/result/__init__.py
benchmarktool/result/ipynb_gen.py
benchmarktool/result/parser.py
benchmarktool/result/result.py
benchmarktool/result/xlsx_gen.py
benchmarktool/resultparser/__init__.py
benchmarktool/resultparser/clasp.py
benchmarktool/runscript/__init__.py
benchmarktool/runscript/parser.py
benchmarktool/runscript/runscript.py
potassco_benchmark_tool-2.2.1.dist-info/licenses/LICENSE
potassco_benchmark_tool-2.2.1.dist-info/METADATA
potassco_benchmark_tool-2.2.1.dist-info/WHEEL
potassco_benchmark_tool-2.2.1.dist-info/entry_points.txt
potassco_benchmark_tool-2.2.1.dist-info/top_level.txt
potassco_benchmark_tool-2.2.1.dist-info/RECORD
