Metadata-Version: 2.4
Name: potassco-benchmark-tool
Version: 2.2.1
Summary: A benchmark-tool for ASP based systems.
Author: Roland Kaminski, Tom Schmidt
License: MIT License
Project-URL: Homepage, https://potassco.org
Project-URL: Repository, https://github.com/potassco/benchmark-tool
Project-URL: Documentation, https://potassco.org/benchmark-tool/
Keywords: benchmarking,benchmarks,Potassco
Requires-Python: >=3.10
License-File: LICENSE
Requires-Dist: lxml
Requires-Dist: pandas
Requires-Dist: xlsxwriter
Requires-Dist: pyarrow
Requires-Dist: nbformat
Provides-Extra: format
Requires-Dist: black; extra == "format"
Requires-Dist: isort; extra == "format"
Requires-Dist: autoflake; extra == "format"
Provides-Extra: lint-pylint
Requires-Dist: pylint; extra == "lint-pylint"
Provides-Extra: typecheck
Requires-Dist: types-setuptools; extra == "typecheck"
Requires-Dist: mypy; extra == "typecheck"
Provides-Extra: test
Requires-Dist: coverage[toml]; extra == "test"
Provides-Extra: doc
Requires-Dist: mkdocs; extra == "doc"
Requires-Dist: mkdocs-material; extra == "doc"
Requires-Dist: mkdocstrings[python]; extra == "doc"
Provides-Extra: dev
Requires-Dist: benchmarktool[lint_pylint,test,typecheck]; extra == "dev"
Provides-Extra: plot
Requires-Dist: plotly; extra == "plot"
Requires-Dist: ipywidgets; extra == "plot"
Requires-Dist: anywidget; extra == "plot"
Requires-Dist: jupyter; extra == "plot"
Dynamic: license-file
